python_spectrometer/__init__.py
python_spectrometer/_audio_manager.py
python_spectrometer/_plot_manager.py
python_spectrometer/core.py
python_spectrometer/daq/__init__.py
python_spectrometer/daq/__init__.pyi
python_spectrometer/daq/atsaverage.py
python_spectrometer/daq/atssimple.py
python_spectrometer/daq/base.py
python_spectrometer/daq/qcodes.py
python_spectrometer/daq/settings.py
python_spectrometer/daq/simulator.py
python_spectrometer/daq/swabian_instruments.py
python_spectrometer/daq/zurich_instruments.py
python_spectrometer-2025.9.1.dist-info/METADATA
python_spectrometer-2025.9.1.dist-info/WHEEL
python_spectrometer-2025.9.1.dist-info/licenses/LICENSE
python_spectrometer-2025.9.1.dist-info/RECORD
