Metadata-Version: 2.4
Name: python-spectrometer
Version: 2025.9.1
Summary: Package to acquire time traces and compute and plot their power spectra
Project-URL: Homepage, https://git.rwth-aachen.de/qutech/python-spectrometer
Author: Quantum Technology Group, RWTH Aachen University
License-Expression: GPL-3.0
License-File: LICENSE
Classifier: Intended Audience :: Science/Research
Classifier: License :: OSI Approved :: GNU General Public License v3 (GPLv3)
Classifier: Programming Language :: Python :: 3
Classifier: Programming Language :: Python :: 3.9
Classifier: Programming Language :: Python :: 3.10
Classifier: Programming Language :: Python :: 3.11
Classifier: Programming Language :: Python :: 3.12
Classifier: Programming Language :: Python :: 3.13
Classifier: Topic :: Scientific/Engineering :: Physics
Classifier: Topic :: Utilities
Requires-Python: >=3.9
Requires-Dist: dill
Requires-Dist: lazy-loader
Requires-Dist: matplotlib>=3.7
Requires-Dist: numpy
Requires-Dist: packaging
Requires-Dist: qutech-util>=2025.05.1
Requires-Dist: scipy
Requires-Dist: typing-extensions>=4.5.0
Provides-Extra: audio-playback
Requires-Dist: pyaudio>=0.2.14; extra == 'audio-playback'
Provides-Extra: complete
Requires-Dist: jupytext; extra == 'complete'
Requires-Dist: myst-parser; extra == 'complete'
Requires-Dist: pyaudio>=0.2.14; extra == 'complete'
Requires-Dist: pydata-sphinx-theme; extra == 'complete'
Requires-Dist: pytest; extra == 'complete'
Requires-Dist: qcodes; extra == 'complete'
Requires-Dist: qcodes-contrib-drivers; extra == 'complete'
Requires-Dist: qopt; extra == 'complete'
Requires-Dist: sphinx; extra == 'complete'
Requires-Dist: zhinst-toolkit>=0.5.0; extra == 'complete'
Provides-Extra: doc
Requires-Dist: jupytext; extra == 'doc'
Requires-Dist: myst-parser; extra == 'doc'
Requires-Dist: pydata-sphinx-theme; extra == 'doc'
Requires-Dist: sphinx; extra == 'doc'
Provides-Extra: qcodes
Requires-Dist: qcodes; extra == 'qcodes'
Requires-Dist: qcodes-contrib-drivers; extra == 'qcodes'
Provides-Extra: simulator
Requires-Dist: qopt; extra == 'simulator'
Provides-Extra: tests
Requires-Dist: pytest; extra == 'tests'
Provides-Extra: zurich-instruments
Requires-Dist: zhinst-toolkit>=0.5.0; extra == 'zurich-instruments'
